GramAddict/__init__.py
GramAddict/__main__.py
GramAddict/version.py
GramAddict/core/__init__.py
GramAddict/core/bot_flow.py
GramAddict/core/config.py
GramAddict/core/decorators.py
GramAddict/core/device_facade.py
GramAddict/core/download_from_github.py
GramAddict/core/filter.py
GramAddict/core/handle_sources.py
GramAddict/core/interaction.py
GramAddict/core/log.py
GramAddict/core/navigation.py
GramAddict/core/persistent_list.py
GramAddict/core/plugin_loader.py
GramAddict/core/report.py
GramAddict/core/resources.py
GramAddict/core/scroll_end_detector.py
GramAddict/core/session_state.py
GramAddict/core/storage.py
GramAddict/core/utils.py
GramAddict/core/views.py
GramAddict/plugins/__init__.py
GramAddict/plugins/action_unfollow_followers.py
GramAddict/plugins/cloned_app.py
GramAddict/plugins/core_arguments.py
GramAddict/plugins/data_analytics.py
GramAddict/plugins/interact_blogger.py
GramAddict/plugins/interact_blogger_followers.py
GramAddict/plugins/interact_blogger_post_likers.py
GramAddict/plugins/interact_feed.py
GramAddict/plugins/interact_hashtag_likers.py
GramAddict/plugins/interact_hashtag_posts.py
GramAddict/plugins/interact_place_likers.py
GramAddict/plugins/interact_place_posts.py
GramAddict/plugins/like_from_urls.py
GramAddict/plugins/plugin.example
GramAddict/plugins/remove_followers.py
GramAddict/plugins/telegram.py
gramaddict-3.2.11.dist-info/entry_points.txt
gramaddict-3.2.11.dist-info/LICENSE
gramaddict-3.2.11.dist-info/WHEEL
gramaddict-3.2.11.dist-info/METADATA
gramaddict-3.2.11.dist-info/RECORD
