Metadata-Version: 2.1
Name: GramAddict
Version: 3.2.11
Summary: Human-like Instagram bot powered by UIAutomator2
Author-email: GramAddict Team <maintainers@gramaddict.org>
Requires-Python: >=3.6
Classifier: License :: Free for non-commercial use
Classifier: Operating System :: OS Independent
Classifier: Programming Language :: Python :: 3
Requires-Dist: colorama==0.4.4
Requires-Dist: ConfigArgParse==1.5.3
Requires-Dist: PyYAML==6.0
Requires-Dist: uiautomator2==2.16.14
Requires-Dist: urllib3==1.26.18
Requires-Dist: emoji==1.6.1
Requires-Dist: langdetect==1.0.9
Requires-Dist: atomicwrites==1.4.0
Requires-Dist: spintax==1.0.4
Requires-Dist: requests~=2.31.0
Requires-Dist: packaging~=20.9
Requires-Dist: matplotlib==3.4.2 ; extra == "analytics"
Requires-Dist: flit ; extra == "dev"
Requires-Dist: pre-commit ; extra == "dev"
Requires-Dist: black ; extra == "dev"
Requires-Dist: flake8 ; extra == "dev"
Requires-Dist: isort ; extra == "dev"
Requires-Dist: ruff ; extra == "dev"
Project-URL: Documentation, https://docs.gramaddict.org/#/
Project-URL: Source, https://github.com/GramAddict/bot
Provides-Extra: analytics
Provides-Extra: dev
